.coveragerc
.gitignore
.isort.cfg
.pre-commit-config.yaml
AUTHORS.rst
CHANGELOG.rst
LICENSE.txt
Makefile
README.rst
requirements.txt
setup.cfg
setup.py
tox.ini
docs/Makefile
docs/authors.rst
docs/changelog.rst
docs/conf.py
docs/index.rst
docs/license.rst
docs/_static/.gitignore
src/juwpyter/__init__.py
src/juwpyter/converter.py
src/juwpyter/jwp.py
src/juwpyter/util.py
src/juwpyter/wp.py
src/juwpyter.egg-info/PKG-INFO
src/juwpyter.egg-info/SOURCES.txt
src/juwpyter.egg-info/dependency_links.txt
src/juwpyter.egg-info/entry_points.txt
src/juwpyter.egg-info/not-zip-safe
src/juwpyter.egg-info/requires.txt
src/juwpyter.egg-info/top_level.txt
src/juwpyter/support/__init__.py
src/juwpyter/support/templates/__init__.py
src/juwpyter/support/templates/basic-x.tpl
src/juwpyter/support/templates/basic.tpl
src/juwpyter/support/templates/celltags.tpl
src/juwpyter/support/templates/hide_input_html.tpl
src/juwpyter/support/templates/hide_input_html_basic.tpl
src/juwpyter/support/templates/html_wordpress.tpl
src/juwpyter/support/templates/markdown_hugo.tpl
src/juwpyter/support/templates/notebook.tplx
support/Template.ipynb
tests/conftest.py
tests/test_skeleton.py
tests/test_data/CityIqPedestrians.ipynb
tests/test_data/Crime Rhythm Maps.ipynb
tests/test_data/multi_para.ipynb
tests/test_data/paragraph.ipynb
tests/test_data/.ipynb_checkpoints/CityIqPedestrians-checkpoint.ipynb
tests/test_data/.ipynb_checkpoints/multi_para-checkpoint.ipynb
tests/test_data/.ipynb_checkpoints/paragraph-checkpoint.ipynb